gitissues/__init__.py
gitissues/classes.py
gitissues/cli.py
gitissues/colour.py
gitissues/utils.py
gitissues-0.0.3.dist-info/LICENSE
gitissues-0.0.3.dist-info/METADATA
gitissues-0.0.3.dist-info/WHEEL
gitissues-0.0.3.dist-info/entry_points.txt
gitissues-0.0.3.dist-info/top_level.txt
gitissues-0.0.3.dist-info/RECORD
